jpip/__init__.py
jpip/hello.py
jpip-0.0.3.dist-info/LICENSE
jpip-0.0.3.dist-info/METADATA
jpip-0.0.3.dist-info/WHEEL
jpip-0.0.3.dist-info/top_level.txt
jpip-0.0.3.dist-info/RECORD
