Metadata-Version: 2.1
Name: jpip
Version: 0.0.3
Summary: basic hello package
Home-page: UNKNOWN
Author: Junichi Shimizu
Author-email: jun.shimi51@gmail.com
License: UNKNOWN
Platform: UNKNOWN
Classifier: Development Status :: 1 - Planning
Classifier: Intended Audience :: Developers
Classifier: Programming Language :: Python :: 3
Classifier: Operating System :: Unix
Classifier: Operating System :: MacOS :: MacOS X
Classifier: Operating System :: Microsoft :: Windows
License-File: LICENSE
